mix_splitter/__init__.py
mix_splitter/argument_parser.py
mix_splitter/downloader.py
mix_splitter/helpers.py
mix_splitter/mix_splitter.py
mix_splitter/random_proxy.py
mix_splitter-0.1.dist-info/LICENSE
mix_splitter-0.1.dist-info/METADATA
mix_splitter-0.1.dist-info/WHEEL
mix_splitter-0.1.dist-info/entry_points.txt
mix_splitter-0.1.dist-info/top_level.txt
mix_splitter-0.1.dist-info/RECORD
