Metadata-Version: 2.1
Name: mix-splitter
Version: 0.1
Summary: Download all the songs in a youtube mix.
Home-page: https://github.com/alexdr00/mix_splitter
Author: Alexander Rendón
Author-email: alexrendon2109@gmail.com
License: MIT
Platform: UNKNOWN
Classifier: Programming Language :: Python :: 3
Classifier: License :: OSI Approved :: MIT License
Requires-Python: >=3.6
Requires-Dist: youtube-dl
Requires-Dist: beautifulsoup4
Requires-Dist: fake-useragent
Requires-Dist: lxml
Requires-Dist: requests
